pheasy/__init__.py
pheasy/basic_io.py
pheasy/constants.py
pheasy/run_pheasy.py
pheasy/version.py
pheasy/core/__init__.py
pheasy/core/cluster_orbit.py
pheasy/core/displacements.py
pheasy/core/forces.py
pheasy/core/optimizer.py
pheasy/core/symmetry_constraints.py
pheasy/core/utilities.py
pheasy/interface/__init__.py
pheasy/interface/gpu_pbte.py
pheasy/interface/phono23py.py
pheasy/interface/qe_d3q.py
pheasy/interface/shengbte.py
pheasy/structure/__init__.py
pheasy/structure/atoms.py
pheasy/structure/force_constants.py
pheasy/structure/io.py
pheasy/structure/symmetry.py
pheasy-0.0.2.data/scripts/pheasy
pheasy-0.0.2.dist-info/LICENSE
pheasy-0.0.2.dist-info/METADATA
pheasy-0.0.2.dist-info/WHEEL
pheasy-0.0.2.dist-info/top_level.txt
pheasy-0.0.2.dist-info/RECORD
