Metadata-Version: 2.1
Name: pheasy
Version: 0.0.2
Summary: A calculator for high-order force constants and phonon quasiparticles.
Home-page: https://gitlab.com/cplin/pheasy
Maintainer: Changpeng Lin
Maintainer-email: changpeng.lin@epfl.ch
Classifier: Programming Language :: Python :: 3
Classifier: Programming Language :: Python :: 3.6
Classifier: Programming Language :: Python :: 3.7
Classifier: Programming Language :: Python :: 3.8
Classifier: License :: OSI Approved :: GNU General Public License v3 (GPLv3)
Classifier: Operating System :: OS Independent
Classifier: Intended Audience :: Science/Research
Classifier: Topic :: Scientific/Engineering :: Physics
Requires-Python: >=3.6
License-File: LICENSE
Requires-Dist: ase >=3.22.1
Requires-Dist: f90nml >=1.3.1
Requires-Dist: spglib >=1.16.3
Requires-Dist: numpy >=1.11.0
Requires-Dist: scipy >=1.4.1
Requires-Dist: scikit-learn >=1.0.2
